semsim/__init__.py
semsim/download.py
semsim/exception.py
semsim/logger.py
semsim/algo/__init__.py
semsim/algo/default.py
semsim/algo/engine.py
semsim/algo/filter.py
semsim/algo/heuristic.py
semsim/algo/kernel.py
semsim/algo/neural.py
semsim/algo/parser.py
semsim/algo/representation.py
semsim/algo/tag.py
semsim/algo/tree.py
semsim/interface/__init__.py
semsim/interface/cli.py
semsim-1.1.1.dist-info/LICENSE
semsim-1.1.1.dist-info/METADATA
semsim-1.1.1.dist-info/WHEEL
semsim-1.1.1.dist-info/entry_points.txt
semsim-1.1.1.dist-info/top_level.txt
semsim-1.1.1.dist-info/RECORD
