Metadata-Version: 2.1
Name: semsim
Version: 1.1.1
Summary: A free tool for sentence similarity evaluation
Home-page: https://gitlab.com/Mathematician2000/semsim
Author: David Avagyan
Author-email: david_avagyan@list.ru
License: BSD 3-Clause License
Project-URL: Homepage, https://gitlab.com/Mathematician2000/semsim
Project-URL: Documentation, https://pysemsim.readthedocs.io/
Keywords: NLP,dependency parsing,CoNLL-U,sentence similarity
Classifier: Programming Language :: Python :: 3
Classifier: Programming Language :: Python :: 3.9
Classifier: Environment :: Console
Classifier: Operating System :: OS Independent
Requires-Python: >=3.9
License-File: LICENSE
Requires-Dist: attrs
Requires-Dist: click
Requires-Dist: networkx
Requires-Dist: numpy
Requires-Dist: pymorphy2
Requires-Dist: scipy
Requires-Dist: simple-elmo
Requires-Dist: tensorflow
Requires-Dist: tensorrt
Requires-Dist: textract
Requires-Dist: torch
Requires-Dist: torch-geometric
Requires-Dist: torch-scatter
Requires-Dist: torch-sparse
Requires-Dist: torchwordemb
Requires-Dist: tqdm
Requires-Dist: ufal.udpipe
